Metadata-Version: 2.1
Name: SnipBin.py
Version: 1.0.1.3
Summary: A Python API wrapper for SnipBin (http://snip.hxrsh.in/)
Home-page: https://github.com/airD173/SnipBin.py
Author: Atri Dey
Author-email: adey1731@gmail.com
License: UNKNOWN
Project-URL: Bug Reports, https://github.com/airD173/SnipBin.py/issues
Keywords: api,wrapper,paste,snipbin
Platform: UNKNOWN
Classifier: Development Status :: 5 - Production/Stable
Classifier: Intended Audience :: Developers
Classifier: License :: OSI Approved :: MIT License
Classifier: Programming Language :: Python :: 3
Classifier: Programming Language :: Python :: 3.6
Classifier: Programming Language :: Python :: 3.7
Classifier: Programming Language :: Python :: 3.8
Classifier: Programming Language :: Python :: 3.9
Classifier: Programming Language :: Python :: 3.10
Classifier: Programming Language :: Python :: 3 :: Only
Requires-Python: >=3.6, <4
